jalali_calendar_cli/__init__.py
jalali_calendar_cli/holidays.json
jalali_calendar_cli/jalali_calendar.py
jalali_calendar_cli-0.1.8.dist-info/entry_points.txt
jalali_calendar_cli-0.1.8.dist-info/WHEEL
jalali_calendar_cli-0.1.8.dist-info/METADATA
jalali_calendar_cli-0.1.8.dist-info/RECORD
