Metadata-Version: 2.1
Name: jalali-calendar-cli
Version: 0.1.8
Summary: Jalali (Shamsi) calendar in your terminal, with holidays
Author: NightMachinery
Author-email: feraidoonmehri@gmail.com
Requires-Python: >=3.10,<4.0
Classifier: Programming Language :: Python :: 3
Classifier: Programming Language :: Python :: 3.10
Classifier: Programming Language :: Python :: 3.11
Requires-Dist: colorama (>=0.4.6,<0.5.0)
Requires-Dist: jdatetime (>=4.1.1,<5.0.0)
